mu/__init__.py
mu/__main__.py
mu/util.py
mu_xml-0.1.3.dist-info/METADATA
mu_xml-0.1.3.dist-info/WHEEL
mu_xml-0.1.3.dist-info/entry_points.txt
mu_xml-0.1.3.dist-info/licenses/LICENSE
mu_xml-0.1.3.dist-info/RECORD
