Metadata-Version: 2.4
Name: mu-xml
Version: 0.1.3
Summary: Represent HTML and XML using Python data structures.
Project-URL: GitHub, https://github.com/Collage-CMS/mu
Author-email: xokomola <marc.van.grootel@gmail.com>
License-Expression: MIT
License-File: LICENSE
Keywords: html,templates,xml
Classifier: Development Status :: 3 - Alpha
Classifier: Intended Audience :: Developers
Classifier: License :: OSI Approved :: MIT License
Classifier: Operating System :: OS Independent
Classifier: Programming Language :: Python :: 3.12
Classifier: Topic :: Text Processing :: Markup :: HTML
Classifier: Topic :: Text Processing :: Markup :: XML
Requires-Python: >=3.12
Requires-Dist: pyyaml==6.0.2
